CreateUser/__init__.py
CreateUser/user_creation.py
simple_user_creation-0.2.0.dist-info/METADATA
simple_user_creation-0.2.0.dist-info/WHEEL
simple_user_creation-0.2.0.dist-info/top_level.txt
simple_user_creation-0.2.0.dist-info/RECORD
